{"devicePlatform":"","logFolder":"C:\\Training\\API Testing\\APITestingTheMovieDB\\Reports\\TV Seasons\\02 TV Season TV Airing Today and\\20181212_162728","runData":{"hostName":"hatha - DESKTOP-EG6P0UN.attlocal.net","hostAddress":"192.168.1.80","os":"Windows 10 64bit","katalonVersion":"5.8.5.1"},"type":"TEST_SUITE","name":"02 TV Season TV Airing Today and","id":"Test Suites/TV Seasons/02 TV Season TV Airing Today and","source":"","message":"Test Cases/TV Seasons/08 Get TV Airing Today Get Videos","description":"","startTime":1544650051169,"endTime":1544650056169,"childRecords":[{"isOptional":false,"type":"TEST_CASE","name":"Test Cases/TV Seasons/06 Get TV Airing Today Get External IDs","id":"Test Cases/TV Seasons/06 Get TV Airing Today Get External IDs","source":"C:\\\\Training\\\\API Testing\\\\APITestingTheMovieDB\\\\Test Cases\\\\TV Seasons\\\\06 Get TV Airing Today Get External IDs.tc","message":"Test Cases/TV Seasons/06 Get TV Airing Today Get External IDs","description":"","startTime":1544650051619,"endTime":1544650054077,"childRecords":[{"testStatus":{"stackTrace":"","statusValue":"INFO"},"type":"MESSAGE","name":"","message":"Evaluating variables for test case","startTime":1544650051659,"endTime":0,"childRecords":[],"interuppted":false},{"index":1,"isIgnoredIfFailed":false,"type":"TEST_STEP","name":"Statement - response1 \u003d theMovieDB.TVShow.getTVAiringToday()","message":"Send request successfully","description":"","startTime":1544650052134,"endTime":1544650053534,"childRecords":[{"testStatus":{"stackTrace":"","statusValue":"PASSED"},"type":"MESSAGE","name":"","message":"Send request successfully","startTime":1544650053532,"endTime":0,"childRecords":[],"interuppted":false}],"interuppted":false},{"index":2,"isIgnoredIfFailed":false,"type":"TEST_STEP","name":"Statement - TVID \u003d theMovieDB.TVShow.getRandomTV(response1)","description":"","startTime":1544650053536,"endTime":1544650053616,"childRecords":[],"interuppted":false},{"index":3,"isIgnoredIfFailed":false,"type":"TEST_STEP","name":"Statement - response1 \u003d theMovieDB.TVShow.getDetails(TVID)","message":"Send request successfully","description":"","startTime":1544650053617,"endTime":1544650053864,"childRecords":[{"testStatus":{"stackTrace":"","statusValue":"PASSED"},"type":"MESSAGE","name":"","message":"Send request successfully","startTime":1544650053863,"endTime":0,"childRecords":[],"interuppted":false}],"interuppted":false},{"index":4,"isIgnoredIfFailed":false,"type":"TEST_STEP","name":"Statement - seasonNo \u003d theMovieDB.TVShow.getRandomSeason(response1)","description":"","startTime":1544650053865,"endTime":1544650053868,"childRecords":[],"interuppted":false},{"index":5,"isIgnoredIfFailed":false,"type":"TEST_STEP","name":"Statement - response1 \u003d theMovieDB.TVSeasons.getExternalIDs(TVID, seasonNo)","message":"Send request successfully","description":"","startTime":1544650053869,"endTime":1544650054034,"childRecords":[{"testStatus":{"stackTrace":"","statusValue":"PASSED"},"type":"MESSAGE","name":"","message":"Send request successfully","startTime":1544650054033,"endTime":0,"childRecords":[],"interuppted":false}],"interuppted":false},{"index":6,"isIgnoredIfFailed":false,"type":"TEST_STEP","name":"Statement - theMovieDB.TheMovieDBCommon.printDataValue(response1, \"TV Seasons/Get External IDs for TVID: \" + TVID + \"; season Number: \" + seasonNo)","description":"","startTime":1544650054035,"endTime":1544650054075,"childRecords":[],"interuppted":false},{"testStatus":{"stackTrace":"","statusValue":"PASSED"},"type":"MESSAGE","name":"","message":"Test Cases/TV Seasons/06 Get TV Airing Today Get External IDs","startTime":1544650054076,"endTime":0,"childRecords":[],"interuppted":false}],"interuppted":false},{"isOptional":false,"type":"TEST_CASE","name":"Test Cases/TV Seasons/07 Get TV Airing Today Get Images","id":"Test Cases/TV Seasons/07 Get TV Airing Today Get Images","source":"C:\\\\Training\\\\API Testing\\\\APITestingTheMovieDB\\\\Test Cases\\\\TV Seasons\\\\07 Get TV Airing Today Get Images.tc","message":"Test Cases/TV Seasons/07 Get TV Airing Today Get Images","description":"","startTime":1544650054084,"endTime":1544650055094,"childRecords":[{"testStatus":{"stackTrace":"","statusValue":"INFO"},"type":"MESSAGE","name":"","message":"Evaluating variables for test case","startTime":1544650054130,"endTime":0,"childRecords":[],"interuppted":false},{"index":1,"isIgnoredIfFailed":false,"type":"TEST_STEP","name":"Statement - response1 \u003d theMovieDB.TVShow.getTVAiringToday()","message":"Send request successfully","description":"","startTime":1544650054584,"endTime":1544650054768,"childRecords":[{"testStatus":{"stackTrace":"","statusValue":"PASSED"},"type":"MESSAGE","name":"","message":"Send request successfully","startTime":1544650054768,"endTime":0,"childRecords":[],"interuppted":false}],"interuppted":false},{"index":2,"isIgnoredIfFailed":false,"type":"TEST_STEP","name":"Statement - TVID \u003d theMovieDB.TVShow.getRandomTV(response1)","description":"","startTime":1544650054769,"endTime":1544650054772,"childRecords":[],"interuppted":false},{"index":3,"isIgnoredIfFailed":false,"type":"TEST_STEP","name":"Statement - response1 \u003d theMovieDB.TVShow.getDetails(TVID)","message":"Send request successfully","description":"","startTime":1544650054773,"endTime":1544650054918,"childRecords":[{"testStatus":{"stackTrace":"","statusValue":"PASSED"},"type":"MESSAGE","name":"","message":"Send request successfully","startTime":1544650054915,"endTime":0,"childRecords":[],"interuppted":false}],"interuppted":false},{"index":4,"isIgnoredIfFailed":false,"type":"TEST_STEP","name":"Statement - seasonNo \u003d theMovieDB.TVShow.getRandomSeason(response1)","description":"","startTime":1544650054919,"endTime":1544650054926,"childRecords":[],"interuppted":false},{"index":5,"isIgnoredIfFailed":false,"type":"TEST_STEP","name":"Statement - response1 \u003d theMovieDB.TVSeasons.getImages(TVID, seasonNo)","message":"Send request successfully","description":"","startTime":1544650054928,"endTime":1544650055088,"childRecords":[{"testStatus":{"stackTrace":"","statusValue":"PASSED"},"type":"MESSAGE","name":"","message":"Send request successfully","startTime":1544650055087,"endTime":0,"childRecords":[],"interuppted":false}],"interuppted":false},{"index":6,"isIgnoredIfFailed":false,"type":"TEST_STEP","name":"Statement - theMovieDB.TheMovieDBCommon.printDataValue(response1, \"TV Seasons/Get Images for TVID: \" + TVID + \"; season Number: \" + seasonNo)","description":"","startTime":1544650055088,"endTime":1544650055092,"childRecords":[],"interuppted":false},{"testStatus":{"stackTrace":"","statusValue":"PASSED"},"type":"MESSAGE","name":"","message":"Test Cases/TV Seasons/07 Get TV Airing Today Get Images","startTime":1544650055092,"endTime":0,"childRecords":[],"interuppted":false}],"interuppted":false},{"isOptional":false,"type":"TEST_CASE","name":"Test Cases/TV Seasons/08 Get TV Airing Today Get Videos","id":"Test Cases/TV Seasons/08 Get TV Airing Today Get Videos","source":"C:\\\\Training\\\\API Testing\\\\APITestingTheMovieDB\\\\Test Cases\\\\TV Seasons\\\\08 Get TV Airing Today Get Videos.tc","message":"Test Cases/TV Seasons/08 Get TV Airing Today Get Videos","description":"","startTime":1544650055098,"endTime":1544650056102,"childRecords":[{"testStatus":{"stackTrace":"","statusValue":"INFO"},"type":"MESSAGE","name":"","message":"Evaluating variables for test case","startTime":1544650055107,"endTime":0,"childRecords":[],"interuppted":false},{"index":1,"isIgnoredIfFailed":false,"type":"TEST_STEP","name":"Statement - response1 \u003d theMovieDB.TVShow.getTVAiringToday()","message":"Send request successfully","description":"","startTime":1544650055581,"endTime":1544650055788,"childRecords":[{"testStatus":{"stackTrace":"","statusValue":"PASSED"},"type":"MESSAGE","name":"","message":"Send request successfully","startTime":1544650055787,"endTime":0,"childRecords":[],"interuppted":false}],"interuppted":false},{"index":2,"isIgnoredIfFailed":false,"type":"TEST_STEP","name":"Statement - TVID \u003d theMovieDB.TVShow.getRandomTV(response1)","description":"","startTime":1544650055788,"endTime":1544650055791,"childRecords":[],"interuppted":false},{"index":3,"isIgnoredIfFailed":false,"type":"TEST_STEP","name":"Statement - response1 \u003d theMovieDB.TVShow.getDetails(TVID)","message":"Send request successfully","description":"","startTime":1544650055791,"endTime":1544650055948,"childRecords":[{"testStatus":{"stackTrace":"","statusValue":"PASSED"},"type":"MESSAGE","name":"","message":"Send request successfully","startTime":1544650055947,"endTime":0,"childRecords":[],"interuppted":false}],"interuppted":false},{"index":4,"isIgnoredIfFailed":false,"type":"TEST_STEP","name":"Statement - seasonNo \u003d theMovieDB.TVShow.getRandomSeason(response1)","description":"","startTime":1544650055949,"endTime":1544650055950,"childRecords":[],"interuppted":false},{"index":5,"isIgnoredIfFailed":false,"type":"TEST_STEP","name":"Statement - response1 \u003d theMovieDB.TVSeasons.getVideos(TVID, seasonNo)","message":"Send request successfully","description":"","startTime":1544650055953,"endTime":1544650056094,"childRecords":[{"testStatus":{"stackTrace":"","statusValue":"PASSED"},"type":"MESSAGE","name":"","message":"Send request successfully","startTime":1544650056093,"endTime":0,"childRecords":[],"interuppted":false}],"interuppted":false},{"index":6,"isIgnoredIfFailed":false,"type":"TEST_STEP","name":"Statement - theMovieDB.TheMovieDBCommon.printDataValue(response1, \"TV Seasons/Get Videos for TVID: \" + TVID + \"; season Number: \" + seasonNo)","description":"","startTime":1544650056095,"endTime":1544650056098,"childRecords":[],"interuppted":false},{"testStatus":{"stackTrace":"","statusValue":"PASSED"},"type":"MESSAGE","name":"","message":"Test Cases/TV Seasons/08 Get TV Airing Today Get Videos","startTime":1544650056101,"endTime":0,"childRecords":[],"interuppted":false}],"interuppted":false}],"interuppted":false}